<?xml version="1.0" encoding="utf-8"?>
<!DOCTYPE documentInfo>
<documentInfo url="/home/chris/college/modeling/hw-2/hw-2.pdf">
 <pageList/>
 <generalInfo>
  <history>
   <oldPage viewport="0"/>
   <oldPage viewport="4;C2:0.497351:0.60502:1"/>
   <oldPage viewport="2;C2:0.49508:0.955798:1"/>
   <oldPage viewport="3;C2:0.49508:0.971008:1"/>
   <current viewport="4;C2:0.49508:0.472909:1"/>
  </history>
  <views>
   <view name="PageView">
    <zoom mode="0" value="0.895768"/>
   </view>
  </views>
 </generalInfo>
</documentInfo>
